[
  {
    "id":1,
    "fileName":"2016年市级以上重点龙头企业正式名单-1.xlsx",
    "cache":{
      "id":1,
      "percent":100,
      "tableName":"ETL_BUFF_XXX",
      "status":"10"
    },
    "clean":{
      "id":2,
      "percent":90,
      "tableName":"ETL_WASH_XXX",
      "status":"1"
    },
    "convert":{

    },
    "validate":{

    }
  },
  {
    "id":2,
    "fileName":"2016年市级以上重点龙头企业正式名单-2.xlsx",
    "cache":{
      "id":1,
      "percent":100,
      "tableName":"ETL_BUFF_XXX",
      "status":"10"
    },
    "clean":{
      "id":2,
      "percent":100,
      "tableName":"ETL_WASH_XXX",
      "status":"10"
    },
    "convert":{
      "id":3,
      "percent":40,
      "tableName":"ETL_TRANS_XXX",
      "status":"5"
    },
    "validate":{

    }
  },
  {
    "id":3,
    "fileName":"2016年市级以上重点龙头企业正式名单-3.xlsx",
    "cache":{
      "id":1,
      "percent":100,
      "tableName":"ETL_BUFF_XXX",
      "status":"10"
    },
    "clean":{
      "id":2,
      "percent":100,
      "tableName":"ETL_WASH_XXX",
      "status":"10"
    },
    "convert":{
      "id":3,
      "percent":20,
      "tableName":"ETL_TRANS_XXX",
      "status":"30"
    },
    "validate":{

    }
  },
  {
    "id":4,
    "fileName":"2016年市级以上重点龙头企业正式名单-4.xlsx",
    "cache":{
      "id":1,
      "percent":100,
      "tableName":"ETL_BUFF_XXX",
      "status":"10"
    },
    "clean":{
      "id":2,
      "percent":100,
      "tableName":"ETL_WASH_XXX",
      "status":"10"
    },
    "convert":{
      "id":3,
      "percent":100,
      "tableName":"ETL_TRANS_XXX",
      "status":"10"
    },
    "validate":{
      "id":4,
      "percent":100,
      "tableName":"ETL_TRANS_XXX",
      "status":"10"
    }
  }
]
